AGuideToPortingCCToRust/README.md
AGuideToPortingCCToRust/__init__.py
AGuideToPortingCCToRust/__main__.py
AGuideToPortingCCToRust/file.epub
AGuideToPortingCCToRust/index.html
AGuideToPortingCCToRust/css/__init__.py
AGuideToPortingCCToRust/css/annotations.css
AGuideToPortingCCToRust/css/main.css
AGuideToPortingCCToRust/css/normalize.css
AGuideToPortingCCToRust/css/popup.css
AGuideToPortingCCToRust/font/__init__.py
AGuideToPortingCCToRust/font/fontello.eot
AGuideToPortingCCToRust/font/fontello.svg
AGuideToPortingCCToRust/font/fontello.ttf
AGuideToPortingCCToRust/font/fontello.woff
AGuideToPortingCCToRust/img/__init__.py
AGuideToPortingCCToRust/img/annotator-glyph-sprite.png
AGuideToPortingCCToRust/img/annotator-icon-sprite.png
AGuideToPortingCCToRust/img/apple-touch-icon.png
AGuideToPortingCCToRust/img/cancelfullscreen.png
AGuideToPortingCCToRust/img/close.png
AGuideToPortingCCToRust/img/fullscreen.png
AGuideToPortingCCToRust/img/loader.gif
AGuideToPortingCCToRust/img/menu-icon.png
AGuideToPortingCCToRust/img/save.png
AGuideToPortingCCToRust/img/saved.png
AGuideToPortingCCToRust/img/settings-s.png
AGuideToPortingCCToRust/img/settings.png
AGuideToPortingCCToRust/img/star.png
AGuideToPortingCCToRust/js/__init__.py
AGuideToPortingCCToRust/js/epub.js
AGuideToPortingCCToRust/js/epub.min.js
AGuideToPortingCCToRust/js/epub.min.map
AGuideToPortingCCToRust/js/hooks.min.js
AGuideToPortingCCToRust/js/hooks.min.map
AGuideToPortingCCToRust/js/reader.js
AGuideToPortingCCToRust/js/reader.js.map
AGuideToPortingCCToRust/js/reader.min.js
AGuideToPortingCCToRust/js/reader.min.map
AGuideToPortingCCToRust/js/hooks/__init__.py
AGuideToPortingCCToRust/js/hooks/extensions/__init__.py
AGuideToPortingCCToRust/js/hooks/extensions/highlight.js
AGuideToPortingCCToRust/js/libs/__init__.py
AGuideToPortingCCToRust/js/libs/jquery.min.js
AGuideToPortingCCToRust/js/libs/localforage.min.js
AGuideToPortingCCToRust/js/libs/screenfull.js
AGuideToPortingCCToRust/js/libs/screenfull.min.js
a_guide_to_porting_c_c_to_rust-2024.3.3.0.dist-info/METADATA
a_guide_to_porting_c_c_to_rust-2024.3.3.0.dist-info/WHEEL
a_guide_to_porting_c_c_to_rust-2024.3.3.0.dist-info/entry_points.txt
a_guide_to_porting_c_c_to_rust-2024.3.3.0.dist-info/top_level.txt
a_guide_to_porting_c_c_to_rust-2024.3.3.0.dist-info/RECORD
